setup_serv.py
mes_server_prod.egg-info/PKG-INFO
mes_server_prod.egg-info/SOURCES.txt
mes_server_prod.egg-info/dependency_links.txt
mes_server_prod.egg-info/requires.txt
mes_server_prod.egg-info/top_level.txt
server/__init__.py
server/server.py
server/build/__init__.py
server/build/lib/__init__.py
server/build/lib/common/__init__.py
server/build/lib/common/decos.py
server/build/lib/common/descryptors.py
server/build/lib/common/errors.py
server/build/lib/common/metaclasses.py
server/build/lib/common/utils.py
server/build/lib/common/variables.py
server/build/lib/logs/__init__.py
server/build/lib/logs/config_client_log.py
server/build/lib/logs/config_server_log.py
server/build/lib/server/__init__.py
server/build/lib/server/add_user.py
server/build/lib/server/config_window.py
server/build/lib/server/core.py
server/build/lib/server/database.py
server/build/lib/server/main_window.py
server/build/lib/server/remove_user.py
server/build/lib/server/stat_window.py
server/build/lib/unit_tests/__init__.py
server/common/__init__.py
server/common/decos.py
server/common/descryptors.py
server/common/errors.py
server/common/metaclasses.py
server/common/utils.py
server/common/variables.py
server/doc/__init__.py
server/doc/source/__init__.py
server/doc/source/conf.py
server/logs/__init__.py
server/logs/config_client_log.py
server/logs/config_server_log.py
server/server/__init__.py
server/server/add_user.py
server/server/config_window.py
server/server/core.py
server/server/database.py
server/server/main_window.py
server/server/remove_user.py
server/server/stat_window.py
server/unit_tests/__init__.py