Metadata-Version: 2.1
Name: mes-server-prod
Version: 0.0.1
Summary: mes_server_prod
Home-page: UNKNOWN
Author: Ruslan Zakirov
Author-email: zakirovra@gmail.com
License: UNKNOWN
Platform: UNKNOWN
